feature_engineering/__init__.py
feature_engineering/encoding.py
feature_engineering/selection.py
feature_engineering/transformation.py
feature_engineering_nikel-0.1.0.dist-info/licenses/LICENSE
feature_engineering_nikel-0.1.0.dist-info/METADATA
feature_engineering_nikel-0.1.0.dist-info/WHEEL
feature_engineering_nikel-0.1.0.dist-info/top_level.txt
feature_engineering_nikel-0.1.0.dist-info/RECORD
