Metadata-Version: 2.4
Name: feature_engineering_nikel
Version: 0.1.0
Summary: A short human-friendly description of your package
Home-page: https://github.com/aditnikel/fds-v2-ai-ml/tree/main/services/feature_pipeline
Author: Ratu, Adityano W
Author-email: "A.W.Ratu" <adityano@nikel.com>
License: MIT License
Project-URL: Homepage, https://github.com/aditnikel/fds-v2-ai-ml/tree/main/services/feature_pipeline
Project-URL: Bug Tracker, https://github.com/impact-credit-solutions/fds-v2-ai-ml/issues
Requires-Python: >=3.9.0
License-File: LICENSE
Requires-Dist: numpy
Requires-Dist: pandas
Requires-Dist: scikit-learn
Requires-Dist: scipy
Dynamic: author
Dynamic: home-page
Dynamic: license-file
Dynamic: requires-python
